{
"type": "FeatureCollection",
"crs": { "type": "name", "properties": { "name": "urn:ogc:def:crs:OGC:1.3:CRS84" } },
"features": [
{ "type": "Feature", "properties": { }, "geometry": { "type": "Point", "coordinates": [ -0.136668, 51.513341 ] } },
{ "type": "Feature", "properties": { }, "geometry": { "type": "Point", "coordinates": [ -0.139586, 51.513876 ] } },
{ "type": "Feature", "properties": { }, "geometry": { "type": "Point", "coordinates": [ -0.139671, 51.514906 ] } },
{ "type": "Feature", "properties": { }, "geometry": { "type": "Point", "coordinates": [ -0.13163, 51.512354 ] } },
{ "type": "Feature", "properties": { }, "geometry": { "type": "Point", "coordinates": [ -0.133594, 51.512139 ] } },
{ "type": "Feature", "properties": { }, "geometry": { "type": "Point", "coordinates": [ -0.135919, 51.511542 ] } },
{ "type": "Feature", "properties": { }, "geometry": { "type": "Point", "coordinates": [ -0.133962, 51.510019 ] } },
{ "type": "Feature", "properties": { }, "geometry": { "type": "Point", "coordinates": [ -0.138199, 51.511295 ] } }
]
}
